autotools/__init__.py
autotools/cli.py
autotools/autocaps/__init__.py
autotools/autocaps/commands.py
autotools/autocaps/core.py
autotools/autoip/__init__.py
autotools/autoip/commands.py
autotools/autoip/core.py
autotools/autolower/__init__.py
autotools/autolower/commands.py
autotools/autolower/core.py
autotools/autopassword/__init__.py
autotools/autopassword/commands.py
autotools/autopassword/core.py
autotools/autotest/__init__.py
autotools/autotest/commands.py
autotools/utils/__init__.py
autotools/utils/commands.py
autotools/utils/loading.py
autotools/utils/performance.py
autotools/utils/requirements.py
autotools/utils/text.py
autotools/utils/updates.py
autotools/utils/version.py
open_autotools-0.0.4.dist-info/licenses/LICENSE
open_autotools-0.0.4.dist-info/METADATA
open_autotools-0.0.4.dist-info/WHEEL
open_autotools-0.0.4.dist-info/entry_points.txt
open_autotools-0.0.4.dist-info/top_level.txt
open_autotools-0.0.4.dist-info/RECORD
