Metadata-Version: 2.4
Name: Open-AutoTools
Version: 0.0.4
Summary: A suite of automated tools accessible via CLI with a simple `autotools` command
Home-page: https://github.com/BabylooPro/Open-AutoTools
Author: BabylooPro
Author-email: maxremy.dev@gmail.com
License: MIT
Project-URL: Bug Tracker, https://github.com/BabylooPro/Open-AutoTools/issues
Classifier: Programming Language :: Python :: 3.10
Classifier: Programming Language :: Python :: 3.11
Classifier: Programming Language :: Python :: 3.12
Classifier: Operating System :: OS Independent
Requires-Python: >=3.10
License-File: LICENSE
Requires-Dist: click>=8.1.3
Requires-Dist: requests>=2.31.0
Requires-Dist: python-dotenv>=1.0.0
Requires-Dist: packaging>=23.0
Requires-Dist: halo>=0.0.31
Requires-Dist: pyperclip>=1.8.2
Requires-Dist: netifaces>=0.11.0
Requires-Dist: speedtest-cli>=2.1.3
Requires-Dist: psutil>=5.9.0
Requires-Dist: cryptography>=42.0.2
Provides-Extra: dev
Dynamic: author
Dynamic: author-email
Dynamic: classifier
Dynamic: description
Dynamic: description-content-type
Dynamic: home-page
Dynamic: license
Dynamic: license-file
Dynamic: project-url
Dynamic: provides-extra
Dynamic: requires-dist
Dynamic: requires-python
Dynamic: summary
